[{"created_time": "2018-02-09T08:47:00+0000", "story": null, "post_id": "462508190484900_1686845528051154", "message": "#12438 I have reached a point where I simultaneously have crushes on two girls. I don't know what to do about this. I mean... I know that all my crushes so far have only led to me being sad and writing depressing poetry. But how can I write a poem when I don't even know who I'm said about.", "comments": 7, "reactions": {"like": 20, "love": 4, "wow": 2, "haha": 6, "sorry": 2}, "page_data": {"page_fans": 20930, "page_engaged_users": 4053, "page_views": 4978, "page_consumption": 18393}}, {"created_time": "2018-02-09T08:43:01+0000", "story": null, "post_id": "462508190484900_1686842938051413", "message": "#12428 guy at the gym's neck veins looked like they were going to explode. is that even healthy \"bro\"", "comments": 2, "reactions": {"like": 4}, "page_data": {"page_fans": 20930, "page_engaged_users": 4053, "page_views": 4978, "page_consumption": 18393}}, {"created_time": "2018-02-09T08:42:00+0000", "story": null, "post_id": "462508190484900_1686840494718324", "message": "#12425 I had a dream last night that Unified's start time was moved to 5:30AM because we were doing too good at staying awake for the 9-11 every day of the week", "comments": 14, "reactions": {"like": 47, "wow": 2, "haha": 22, "sorry": 12, "anger": 2}, "page_data": {"page_fans": 20930, "page_engaged_users": 4053, "page_views": 4978, "page_consumption": 18393}}, {"created_time": "2018-02-09T08:40:00+0000", "story": null, "post_id": "462508190484900_1686838804718493", "message": "#12423 @#12410 In the event that this isn't a troll, one of the most intellectually challenging people I met late in my undergrad at MIT was a Wellesley first-year. I was consistently googling and reading about unfamiliar subjects when talking with this person and it was a humbling experience. Shoutout to our friends from other schools for pulling us out of the MIT tunnel vision and bringing about broader positive discourse :)", "comments": 0, "reactions": {"like": 16, "love": 6}, "page_data": {"page_fans": 20930, "page_engaged_users": 4053, "page_views": 4978, "page_consumption": 18393}}]