[{"created_time": "2017-04-30T21:57:38+0000", "story": "MIT African Students' Association - ASA added an event.", "post_id": "587792247956583_1814855325500360", "message": "Come join us at the BSU Lounge this Sunday and help us enjoy quality food and drinks as we look back and  celebrate the 4 years that our seniors have spent as an integral part of the African Student Association.\n\nDress code = Formal or African Attire", "comments": 0, "reactions": {}, "page_data": {"page_fans": 468, "page_engaged_users": 143, "page_views": 18, "page_consumption": 662}}]